biosimulations_modeldb/__init__.py
biosimulations_modeldb/__main__.py
biosimulations_modeldb/_version.py
biosimulations_modeldb/config.py
biosimulations_modeldb/core.py
biosimulations_modeldb/utils.py
biosimulations_modeldb/final/curators.yml
biosimulations_modeldb/final/file-ext-format-uri-map.yml
biosimulations_modeldb/final/issues.yml
biosimulations_modeldb/final/modeldb-bqbiol-map.yml
biosimulations_modeldb/final/set-file-map.yml
biosimulations_modeldb/final/status.yml
biosimulations_modeldb/final/taxa.yml
biosimulations_modeldb-0.0.4.dist-info/LICENSE
biosimulations_modeldb-0.0.4.dist-info/METADATA
biosimulations_modeldb-0.0.4.dist-info/WHEEL
biosimulations_modeldb-0.0.4.dist-info/entry_points.txt
biosimulations_modeldb-0.0.4.dist-info/top_level.txt
biosimulations_modeldb-0.0.4.dist-info/RECORD
