Metadata-Version: 2.1
Name: biosimulations-modeldb
Version: 0.0.4
Summary: Command-line program for publishing the ModelDB model repository to BioSimulations.
Home-page: https://github.com/biosimulations/biosimulations-modeldb
Download-URL: https://github.com/biosimulations/biosimulations-modeldb
Author: Center for Reproducible Biomedical Modeling
Author-email: info@biosimulations.org
License: MIT
Keywords: neuroscience,systems biology,computational biology,mathematical modeling,numerical simulation,XPP,ModelDB
Platform: UNKNOWN
Classifier: Development Status :: 3 - Alpha
Classifier: Intended Audience :: Science/Research
Classifier: License :: OSI Approved :: MIT License
Classifier: Topic :: Scientific/Engineering :: Bio-Informatics
License-File: LICENSE
Requires-Dist: beautifulsoup4
Requires-Dist: biopython
Requires-Dist: biosimulators-utils (>=0.1.167)
Requires-Dist: biosimulators-xpp (>=0.0.13)
Requires-Dist: boto3
Requires-Dist: cement
Requires-Dist: gitpython
Requires-Dist: lxml
Requires-Dist: mammoth
Requires-Dist: markdownify
Requires-Dist: natsort
Requires-Dist: numpy
Requires-Dist: python-dateutil
Requires-Dist: python-dotenv
Requires-Dist: pyyaml
Requires-Dist: requests-cache
Requires-Dist: setuptools
Requires-Dist: simplejson
Requires-Dist: termcolor
Provides-Extra: all
Requires-Dist: capturer ; extra == 'all'
Provides-Extra: docs
Provides-Extra: tests
Requires-Dist: capturer ; extra == 'tests'
